jker_mcp_publish_demo/__init__.py
jker_mcp_publish_demo-0.1.2.dist-info/WHEEL
jker_mcp_publish_demo-0.1.2.dist-info/entry_points.txt
jker_mcp_publish_demo-0.1.2.dist-info/METADATA
jker_mcp_publish_demo-0.1.2.dist-info/RECORD
