Metadata-Version: 2.3
Name: jker-mcp-publish-demo
Version: 0.1.2
Summary: use the latest one
Author: Jker
Author-email: Jker <2933385376@qq.com>
Requires-Dist: mcp[cli]>=1.13.0
Requires-Python: >=3.13.3
